Single Cycle/NextPClogic.v
module NextPClogic(NextPC, CurrentPC, SignExtImm64, Branch, ALUZero, Uncondbranch);
	input [63:0] CurrentPC, SignExtImm64;
	input Branch, ALUZero, Uncondbranch;
	output reg [63:0] NextPC;
	
	reg BZero, BranchOR;
	
	always @(*)
		begin
			BZero =  ALUZero & Branch;
			BranchOR = BZero | Uncondbranch;
			if(BranchOR == 1) NextPC =  CurrentPC + (SignExtImm64 << 2);
			else NextPC =  CurrentPC + 4;
		end
endmodule

Lab09/DataMemory.v
`timescale 1ns / 1ps

`define SIZE 1024

module DataMemory(ReadData , Address , WriteData , MemoryRead , MemoryWrite , Clock);
    input [63:0]      WriteData;
    input [63:0]      Address;
    input             Clock, MemoryRead, MemoryWrite;
    output reg [63:0] ReadData;

    reg [7:0]         memBank [`SIZE-1:0];


    // This task is used to write arbitrary data to the Data Memory by
    // the intialization block.
    task initset;
      input [63:0] addr;
      input [63:0] data;
      begin
     memBank[addr] =  data[63:56] ; // Big-endian for the win...
     memBank[addr+1] =  data[55:48];
     memBank[addr+2] =  data[47:40];
     memBank[addr+3] =  data[39:32];
     memBank[addr+4] =  data[31:24];
     memBank[addr+5] =  data[23:16];
     memBank[addr+6] =  data[15:8];
     memBank[addr+7] =  data[7:0];
      end
    endtask


    initial
    begin
        // preseting some data in the data memory used by test #1

        // Address 0x0 gets 0x1
        initset( 64'h0,  64'h1);  //Counter variable
        initset( 64'h8,  64'ha);  //Part of mask
        initset( 64'h10, 64'h5);  //Other part of mask
        initset( 64'h18, 64'h0ffbea7deadbeeff); //big constant
        initset( 64'h20, 64'h0); //clearing space

        // Add any data you need for your tests here.

    end

    // This always block reads the data memory and places a double word
    // on the ReadData bus.
    always @(posedge Clock)
    begin
        if(MemoryRead)
        begin
            ReadData[63:56] <= memBank[Address];
            ReadData[55:48] <=  memBank[Address+1];
            ReadData[47:40] <=  memBank[Address+2];
            ReadData[39:32] <=  memBank[Address+3];
            ReadData[31:24] <=  memBank[Address+4];
            ReadData[23:16] <=  memBank[Address+5];
            ReadData[15:8] <=  memBank[Address+6];
            ReadData[7:0] <=  memBank[Address+7];
        end
    end

    // This always block takes data from the WriteData bus and writes
    // it into the DataMemory.
    always @(posedge Clock)
    begin
        if(MemoryWrite)
        begin
            memBank[Address] <=  WriteData[63:56] ;
            memBank[Address+1] <=  WriteData[55:48];
            memBank[Address+2] <=  WriteData[47:40];
            memBank[Address+3] <=  WriteData[39:32];
            memBank[Address+4] <=  WriteData[31:24];
            memBank[Address+5] <=  WriteData[23:16];
            memBank[Address+6] <=  WriteData[15:8];
            memBank[Address+7] <=  WriteData[7:0];
            // Could be useful for debugging:
            // $display("Writing Address:%h Data:%h",Address, WriteData);
        end
    end
endmodule

Lab09/ALU.v
`define AND   4'b0000
`define OR    4'b0001
`define ADD   4'b0010
`define SUB   4'b0110
`define PassB 4'b0111


module ALU(BusW, BusA, BusB, ALUCtrl, Zero);
    
    parameter n = 64;

    output  [n-1:0] BusW;
    input   [n-1:0] BusA, BusB;
    input   [3:0] ALUCtrl;
    output  Zero;
    
    reg     [n-1:0] BusW;
    
    always @(ALUCtrl or BusA or BusB) begin
        case(ALUCtrl)
            `AND: begin
                BusW <=  BusA & BusB;
            end
            `OR: begin
                BusW <=  BusA | BusB;
            end
            `ADD: begin
                BusW <=  BusA + BusB;
            end
            `SUB: begin
                BusW <=  BusA - BusB;
            end
            `PassB: begin
                BusW <=  BusB;
            end
            default:
                begin
                    BusW = 64'b0;
                    
                end
                
        endcase
    end
    

    assign  Zero = (BusW === 64'h0);
endmodule

Single Cycle/RegisterFile.v
module RegisterFile(BusA, BusB, BusW, RA, RB, RW, RegWr, Clk);
	output [63:0] BusA;
    output [63:0] BusB;
    input [63:0] BusW;
    input [4:0] RA, RB, RW;
    input RegWr;
    input Clk;
    reg [63:0] registers [31:0];


	
    initial
    begin
		registers[31] = 0;
	end
	
	assign BusA = registers[RA];
    assign  BusB = registers[RB];
    
    always @(negedge Clk)
		begin
			if(RegWr == 1 && RW != 31) registers[RW] =  BusW;
		end
	
endmodule

Lab09/SignExtender.v
module SignExtender(BusImm, Imm26, Ctrl); 
  output reg[63:0] BusImm; 
  input [25:0] Imm26; 
  input [2:0] Ctrl; 
  reg extBit; 
 always@(*)
	begin
		case(Ctrl)
			3'b000 : begin // I-type
						 extBit = 1'b0;
						 BusImm = {{52{extBit}}, Imm26[21:10]};
					end
			3'b001 : begin
						 extBit = Imm26[20]; // D-type
						 BusImm = {{55{extBit}}, Imm26[20:12]};
					end
			3'b010 : begin
						 extBit = Imm26[25]; // B-type
						 BusImm = {{38{extBit}}, Imm26};
					end
			3'b011 : begin
						 extBit = Imm26[23]; // CBZ-type
						 BusImm = {{45{extBit}}, Imm26[23:5]};
					end
			3'b100 : begin
						 extBit = 1'b0;
						 case(Imm26[22:21])
						    2'b00 : begin // no shift
						      BusImm = {{48{1'b0}}, Imm26[20:5]};
						    end
						    2'b01 : begin // 16 shift
						      BusImm = {{32{1'b0}}, Imm26[20:5], {16{1'b0}}};
						    end
						    2'b10 : begin // 32 shift
						      BusImm = {{16{1'b0}}, Imm26[20:5], {32{1'b0}}};
						    end
						    2'b11 : begin // 48 shift
						      BusImm = {{0{1'b0}}, Imm26[20:5], {48{1'b0}}};
						    end
						  endcase
						 
						 
					end
			default:
				begin
					BusImm = {64{1'b0}};
				end
		endcase
	end
endmodule

Single Cycle/SingleCycleControl.v
`define OPCODE_ANDREG 11'b?0001010???
`define OPCODE_ORRREG 11'b?0101010???
`define OPCODE_ADDREG 11'b?0?01011???
`define OPCODE_SUBREG 11'b?1?01011???

`define OPCODE_ADDIMM 11'b?0?10001???
`define OPCODE_SUBIMM 11'b?1?10001???

`define OPCODE_MOVZ   11'b110100101??

`define OPCODE_B      11'b?00101?????
`define OPCODE_CBZ    11'b?011010????

`define OPCODE_LDUR   11'b??111000010
`define OPCODE_STUR   11'b??111000000

module control(
    output reg reg2loc,
    output reg alusrc,
    output reg mem2reg,
    output reg regwrite,
    output reg memread,
    output reg memwrite,
    output reg branch,
    output reg uncond_branch,
    output reg [3:0] aluop,
    output reg [2:0] signop,
    input [10:0] opcode
);

always @(*)
begin
    casez (opcode)

        /* Add cases here for each instruction your processor supports */
        `OPCODE_ANDREG: begin
            reg2loc       <= 1'b0;
            alusrc        <= 1'b0;
            mem2reg       <= 1'b0;
            regwrite      <= 1'b1;
            memread       <= 1'b0;
            memwrite      <= 1'b0;
            branch        <= 1'b0;
            uncond_branch <= 1'b0;
            aluop         <= 4'b0000;
            signop        <= 3'bxxx;
        end
        
        `OPCODE_ORRREG: begin
            reg2loc       <= 1'b0;
            alusrc        <= 1'b0;
            mem2reg       <= 1'b0;
            regwrite      <= 1'b1;
            memread       <= 1'b0;
            memwrite      <= 1'b0;
            branch        <= 1'b0;
            uncond_branch <= 1'b0;
            aluop         <= 4'b0001;
            signop        <= 3'bxxx;
        end
        
        `OPCODE_ADDREG: begin
            reg2loc       <= 1'b0;
            alusrc        <= 1'b0;
            mem2reg       <= 1'b0;
            regwrite      <= 1'b1;
            memread       <= 1'b0;
            memwrite      <= 1'b0;
            branch        <= 1'b0;
            uncond_branch <= 1'b0;
            aluop         <= 4'b0010;
            signop        <= 3'bxxx;
        end
        
        `OPCODE_SUBREG: begin
            reg2loc       <= 1'b0;
            alusrc        <= 1'b0;
            mem2reg       <= 1'b0;
            regwrite      <= 1'b1;
            memread       <= 1'b0;
            memwrite      <= 1'b0;
            branch        <= 1'b0;
            uncond_branch <= 1'b0;
            aluop         <= 4'b0110;
            signop        <= 3'bxxx;
        end
        
        `OPCODE_ADDIMM: begin
            reg2loc       <= 1'b0;
            alusrc        <= 1'b0;
            mem2reg       <= 1'b0;
            regwrite      <= 1'b1;
            memread       <= 1'b0;
            memwrite      <= 1'b0;
            branch        <= 1'b0;
            uncond_branch <= 1'b0;
            aluop         <= 4'b0010;
            signop        <= 3'b000;
        end
        
        `OPCODE_SUBIMM: begin
            reg2loc       <= 1'b0;
            alusrc        <= 1'b0;
            mem2reg       <= 1'b0;
            regwrite      <= 1'b1;
            memread       <= 1'b0;
            memwrite      <= 1'b0;
            branch        <= 1'b0;
            uncond_branch <= 1'b0;
            aluop         <= 4'b0110;
            signop        <= 3'b000;
        end
        
        `OPCODE_MOVZ: begin
            reg2loc       <= 1'b0;
            alusrc        <= 1'b1;
            mem2reg       <= 1'b0;
            regwrite      <= 1'b1;
            memread       <= 1'b0;
            memwrite      <= 1'b0;
            branch        <= 1'b0;
            uncond_branch <= 1'b0;
            aluop         <= 4'b0111;
            signop        <= 3'b100;
        end
        
        `OPCODE_B: begin
            reg2loc       <= 1'bx;
            alusrc        <= 1'bx;
            mem2reg       <= 1'bx;
            regwrite      <= 1'b0;
            memread       <= 1'b0;
            memwrite      <= 1'b0;
            branch        <= 1'bx;
            uncond_branch <= 1'b1;
            aluop         <= 4'bxxxx;
            signop        <= 3'b010;
        end
        
        `OPCODE_CBZ: begin
            reg2loc       <= 1'b1;
            alusrc        <= 1'b0;
            mem2reg       <= 1'bx;
            regwrite      <= 1'b0;
            memread       <= 1'b0;
            memwrite      <= 1'b0;
            branch        <= 1'b1;
            uncond_branch <= 1'b0;
            aluop         <= 4'b0111;
            signop        <= 3'b011;
        end
        
        `OPCODE_LDUR: begin
            reg2loc       <= 1'bx;
            alusrc        <= 1'b1;
            mem2reg       <= 1'b1;
            regwrite      <= 1'b1;
            memread       <= 1'b1;
            memwrite      <= 1'b0;
            branch        <= 1'b0;
            uncond_branch <= 1'b0;
            aluop         <= 4'b0010;
            signop        <= 3'b001;
        end
        
        `OPCODE_STUR: begin
            reg2loc       <= 1'b1;
            alusrc        <= 1'b1;
            mem2reg       <= 1'bx;
            regwrite      <= 1'b0;
            memread       <= 1'b0;
            memwrite      <= 1'b1;
            branch        <= 1'b0;
            uncond_branch <= 1'b0;
            aluop         <= 4'b0010;
            signop        <= 3'b001;
        end

        default:
        begin
            reg2loc       <= 1'bx;
            alusrc        <= 1'bx;
            mem2reg       <= 1'bx;
            regwrite      <= 1'b0;
            memread       <= 1'b0;
            memwrite      <= 1'b0;
            branch        <= 1'b0;
            uncond_branch <= 1'b0;
            aluop         <= 4'bxxxx;
            signop        <= 2'bxx;
        end
    endcase
end

endmodule

Lab09/InstructionMemory-1.v
`timescale 1ns / 1ps
/*
 * Module: InstructionMemory
 *
 * Implements read-only instruction memory
 * 
 */
module InstructionMemory(Data, Address);
   parameter T_rd = 20;
   parameter MemSize = 40;
   
   output [31:0] Data;
   input [63:0]  Address;
   reg [31:0] 	 Data;
   
   /*
    * ECEN 350 Processor Test Functions
    * Texas A&M University
    */
   
   always @ (Address) begin
      
      case(Address)

	/* Test Program 1:
	 * Program loads constants from the data memory. Uses these constants to test
	 * the following instructions: LDUR, ORR, AND, CBZ, ADD, SUB, STUR and B.
	 * 
	 * Assembly code for test:
	 * 
	 * 0: LDUR X9, [XZR, 0x0]    //Load 1 into x9
	 * 4: LDUR X10, [XZR, 0x8]   //Load a into x10
	 * 8: LDUR X11, [XZR, 0x10]  //Load 5 into x11
	 * C: LDUR X12, [XZR, 0x18]  //Load big constant into x12
	 * 10: LDUR X13, [XZR, 0x20]  //load a 0 into X13
	 * 
	 * 14: ORR X10, X10, X11  //Create mask of 0xf
	 * 18: AND X12, X12, X10  //Mask off low order bits of big constant
	 * 
	 * loop:
	 * 1C: CBZ X12, end  //while X12 is not 0
	 * 20: ADD X13, X13, X9  //Increment counter in X13
	 * 24: SUB X12, X12, X9  //Decrement remainder of big constant in X12
	 * 28: B loop  //Repeat till X12 is 0
	 * 2C: STUR X13, [XZR, 0x20]  //store back the counter value into the memory location 0x20
	 */
	

	63'h000: Data = 32'hF84003E9;
	63'h004: Data = 32'hF84083EA;
	63'h008: Data = 32'hF84103EB;
	63'h00c: Data = 32'hF84183EC;
	63'h010: Data = 32'hF84203ED;
	63'h014: Data = 32'hAA0B014A;
	63'h018: Data = 32'h8A0A018C;
	63'h01c: Data = 32'hB400008C;
	63'h020: Data = 32'h8B0901AD;
	63'h024: Data = 32'hCB09018C;
	63'h028: Data = 32'h17FFFFFD;
	63'h02c: Data = 32'hF80203ED;
	63'h030: Data = 32'hF84203ED;  //One last load to place stored value on memdbus for test checking.

	/* Add code for your tests here */
	63'h034: Data = 32'hd2e2468e; // MOVZ 1234 X14
	63'h038: Data = 32'hd2cacf0f; // MOVZ 5678 X15
	63'h03c: Data = 32'h8b0f01ce; // ADD X14, X14, X15
	63'h040: Data = 32'hd2b35790; // MOVZ 9ABC X16
	63'h044: Data = 32'hd29bde11; // MOVZ DEF0 X17
	63'h048: Data = 32'h8b110210; // ADD X16, X16, X17
	63'h04c: Data = 32'h8b1001c9; // ADD X9, X14, X16
	63'h050: Data = 32'hF80283E9; // STUR -> 0x28
	63'h054: Data = 32'hF84283EA; // LDUR -> X10

			
	default: Data = 32'hXXXXXXXX;
      endcase
   end
endmodule

Lab09/SingleCycleProc.v
module singlecycle(
    input resetl,
    input [63:0] startpc,
    output reg [63:0] currentpc,
    output [63:0] dmemout,
    input CLK
);

    // Next PC connections
    wire [63:0] nextpc;       // The next PC, to be updated on clock cycle

    // Instruction Memory connections
    wire [31:0] instruction;  // The current instruction

    // Parts of instruction
    wire [4:0] rd;            // The destination register
    wire [4:0] rm;            // Operand 1
    wire [4:0] rn;            // Operand 2
    wire [10:0] opcode;

    // Control wires
    wire reg2loc;
    wire alusrc;
    wire mem2reg;
    wire regwrite;
    wire memread;
    wire memwrite;
    wire branch;
    wire uncond_branch;
    wire [3:0] aluctrl;
    wire [2:0] signop;

    // Register file connections
    wire [63:0] regoutA;     // Output A
    wire [63:0] regoutB;     // Output B

    // ALU connections
    wire [63:0] aluout;
    wire zero;

    // Sign Extender connections
    wire [63:0] extimm;

    // PC update logic
    always @(negedge CLK)
    begin
        if (resetl)
            currentpc <= nextpc;
        else
            currentpc <= startpc;
    end

    // Parts of instruction
    assign rd = instruction[4:0];
    assign rm = instruction[9:5];
    assign rn = reg2loc ? instruction[4:0] : instruction[20:16];
    assign opcode = instruction[31:21];

    InstructionMemory imem(
        .Data(instruction),
        .Address(currentpc)
    );

    control control(
        .reg2loc(reg2loc),
        .alusrc(alusrc),
        .mem2reg(mem2reg),
        .regwrite(regwrite),
        .memread(memread),
        .memwrite(memwrite),
        .branch(branch),
        .uncond_branch(uncond_branch),
        .aluop(aluctrl),
        .signop(signop),
        .opcode(opcode)
    );
    
    
    
    SignExtender SignExtender(
        .BusImm(extimm),
        .Imm26(instruction[25:0]),
        .Ctrl(signop)
    );
    
    
    /*reg [4:0] muxOut5;
    always @(reg2loc)
    begin
    if(reg2loc == 0)
        muxOut5 = rn;
    else
        muxOut5 = rd;
    end*/

    RegisterFile RegisterFile(
        .BusA(regoutA),
        .BusB(regoutB),
        .BusW(muxOutMem),
        .RA(rm),
        .RB(rn),
        .RW(rd),
        .RegWr(regwrite),
        .Clk(CLK)
    );
    
    reg [63:0] muxOut128;
    always @(*)
        begin
            if(alusrc == 0)
                muxOut128 = regoutB;
            else
                muxOut128 = extimm;
        end
    
    ALU ALU(
        .BusW(aluout),
        .BusA(regoutA),
        .BusB(muxOut128),
        .ALUCtrl(aluctrl),
        .Zero(zero)
    );
    
    DataMemory DataMemory(
        .ReadData(dmemout),
        .Address(aluout),
        .WriteData(regoutB),
        .MemoryRead(memread),
        .MemoryWrite(memwrite),
        .Clock(CLK)
    );
    
    reg [63:0] muxOutMem;
    always @(*)
        begin
            if(mem2reg == 0)
                muxOutMem = aluout;
            else
                muxOutMem = dmemout;
        end
    NextPClogic NextPClogic(
        .NextPC(nextpc),
        .CurrentPC(currentpc),
        .SignExtImm64(extimm),
        .Branch(branch),
        .ALUZero(zero),
        .Uncondbranch(uncond_branch)
    );

    /*
    * Connect the remaining datapath elements below.
    * Do not forget any additional multiplexers that may be required.
    */



endmodule

Single Cycle/SingleCycleProcTest.v
`timescale 1ns / 1ps

`define STRLEN 32
`define HalfClockPeriod 60
`define ClockPeriod `HalfClockPeriod * 2

module SingleCycleProcTest_v;

    initial
    begin
        $dumpfile("singlecycle.vcd");
        $dumpvars;
    end

    // These tasks are used to check if a given test has passed and
    // confirm that all tests passed.
    task passTest;
        input [63:0] actualOut, expectedOut;
        input [`STRLEN*8:0] testType;
        inout [7:0] 	  passed;

        if(actualOut == expectedOut) begin $display ("%s passed", testType); passed = passed + 1; end
        else $display ("%s failed: 0x%x should be 0x%x", testType, actualOut, expectedOut);
    endtask

    task allPassed;
        input [7:0] passed;
        input [7:0] numTests;

        if(passed == numTests) $display ("All tests passed");
        else $display("Some tests failed: %d of %d passed", passed, numTests);
    endtask

    // Inputs
    reg        CLK;
    reg        Reset_L;
    reg [63:0] startPC;
    reg [7:0]  passed;
    reg [15:0] watchdog;

    // Outputs
    wire [63:0] dMemOut;
    wire [63:0] currentPC;
    
    initial //This initial block used to dump all wire/reg values to dump file
     begin
       $dumpfile("SingleCycleProcTest.vcd");
       $dumpvars(0,SingleCycleProcTest_v);
     end


    // Instantiate the Unit Under Test (UUT)
    singlecycle uut (
        .CLK(CLK),
        .resetl(Reset_L),
        .startpc(startPC),
        .currentpc(currentPC),
        .dmemout(dMemOut)
    );

    initial begin
        // Initialize Inputs
        Reset_L = 1;
        startPC = 0;
        passed = 0;

        // Initialize Watchdog timer
        watchdog = 0;

        // Wait for global reset
        #(1 * `ClockPeriod);

        // Program 1
        #1
        Reset_L = 0; startPC = 0;
        #(1 * `ClockPeriod);
        Reset_L = 1;

        // ***********************************************************
        // This while loop will continue cycling the processor until the
        // PC reaches the final instruction in the first test.  If the
        // program forms an infinite loop, never reaching the end, the
        // watchdog timer will kick in and kill simulation after 64K
        // cycles.
        // ***********************************************************

        while (currentPC < 64'h34)
        begin
           #(1 * `ClockPeriod);
           $display("CurrentPC:%h",currentPC);
        end
        #(1 * `ClockPeriod);	// One more cycle to load the pass code from the DataMemory.
        passTest(dMemOut, 64'hF, "Results of Program 1", passed);

        // ***********************************************************
        // Add your new tests here
        // ***********************************************************
		while (currentPC <64'h58)
		begin
			#(1*`ClockPeriod);
			$display("CurrentPC:%h", currentPC);
		end
		#(1*`ClockPeriod);
		passTest(dMemOut, 64'h123456789ABCDEF0, "Results of Program 2", passed);
		
        // Done
        allPassed(passed, 2);   // Be sure to change the one to match
                                // the number of tests you add.
        $finish;
    end

    initial begin
        CLK = 0;
    end

    // The following is correct if clock starts at LOW level at StartTime //
    always begin
        #`HalfClockPeriod CLK = ~CLK;
        #`HalfClockPeriod CLK = ~CLK;
        watchdog = watchdog +1;
    end

    // Kill the simulation if the watchdog hits 64K cycles
    always @*
        if (watchdog == 16'hFF)
        begin
            $display("Watchdog Timer Expired.");
            $finish;
        end


endmodule

Single Cycle/singlecycle.vcd
$date
	Thu Aug  4 14:28:59 2022
$end
$version
	Icarus Verilog
$end
$timescale
	1ps
$end
$scope module SingleCycleProcTest_v $end
$var wire 64 ! dMemOut [63:0] $end
$var wire 64 " currentPC [63:0] $end
$var reg 1 # CLK $end
$var reg 1 $ Reset_L $end
$var reg 8 % passed [7:0] $end
$var reg 64 & startPC [63:0] $end
$var reg 16 ' watchdog [15:0] $end
$scope module uut $end
$var wire 1 # CLK $end
$var wire 1 $ resetl $end
$var wire 64 ( startpc [63:0] $end
$var wire 1 ) zero $end
$var wire 1 * uncond_branch $end
$var wire 3 + signop [2:0] $end
$var wire 5 , rn [4:0] $end
$var wire 5 - rm [4:0] $end
$var wire 1 . regwrite $end
$var wire 64 / regoutB [63:0] $end
$var wire 64 0 regoutA [63:0] $end
$var wire 1 1 reg2loc $end
$var wire 5 2 rd [4:0] $end
$var wire 11 3 opcode [10:0] $end
$var wire 64 4 nextpc [63:0] $end
$var wire 1 5 memwrite $end
$var wire 1 6 memread $end
$var wire 1 7 mem2reg $end
$var wire 32 8 instruction [31:0] $end
$var wire 64 9 extimm [63:0] $end
$var wire 64 : dmemout [63:0] $end
$var wire 1 ; branch $end
$var wire 1 < alusrc $end
$var wire 64 = aluout [63:0] $end
$var wire 4 > aluctrl [3:0] $end
$var reg 64 ? currentpc [63:0] $end
$var reg 64 @ muxOut128 [63:0] $end
$var reg 64 A muxOutMem [63:0] $end
$scope module ALU $end
$var wire 64 B BusB [63:0] $end
$var wire 1 ) Zero $end
$var wire 64 C BusA [63:0] $end
$var wire 4 D ALUCtrl [3:0] $end
$var reg 64 E BusW [63:0] $end
$upscope $end
$scope module DataMemory $end
$var wire 64 F Address [63:0] $end
$var wire 1 # Clock $end
$var wire 64 G WriteData [63:0] $end
$var wire 1 5 MemoryWrite $end
$var wire 1 6 MemoryRead $end
$var reg 64 H ReadData [63:0] $end
$scope task initset $end
$var reg 64 I addr [63:0] $end
$var reg 64 J data [63:0] $end
$upscope $end
$upscope $end
$scope module NextPClogic $end
$var wire 1 ) ALUZero $end
$var wire 64 K CurrentPC [63:0] $end
$var wire 1 * Uncondbranch $end
$var wire 64 L SignExtImm64 [63:0] $end
$var wire 1 ; Branch $end
$var reg 1 M BZero $end
$var reg 1 N BranchOR $end
$var reg 64 O NextPC [63:0] $end
$upscope $end
$scope module RegisterFile $end
$var wire 64 P BusA [63:0] $end
$var wire 64 Q BusB [63:0] $end
$var wire 64 R BusW [63:0] $end
$var wire 1 # Clk $end
$var wire 5 S RA [4:0] $end
$var wire 5 T RB [4:0] $end
$var wire 5 U RW [4:0] $end
$var wire 1 . RegWr $end
$upscope $end
$scope module SignExtender $end
$var wire 26 V Imm26 [25:0] $end
$var wire 3 W Ctrl [2:0] $end
$var reg 64 X BusImm [63:0] $end
$var reg 1 Y extBit $end
$upscope $end
$scope module control $end
$var wire 11 Z opcode [10:0] $end
$var reg 4 [ aluop [3:0] $end
$var reg 1 < alusrc $end
$var reg 1 ; branch $end
$var reg 1 7 mem2reg $end
$var reg 1 6 memread $end
$var reg 1 5 memwrite $end
$var reg 1 1 reg2loc $end
$var reg 1 . regwrite $end
$var reg 3 \ signop [2:0] $end
$var reg 1 * uncond_branch $end
$upscope $end
$scope module imem $end
$var wire 64 ] Address [63:0] $end
$var reg 32 ^ Data [31:0] $end
$upscope $end
$upscope $end
$scope task allPassed $end
$var reg 8 _ numTests [7:0] $end
$var reg 8 ` passed [7:0] $end
$upscope $end
$scope task passTest $end
$var reg 64 a actualOut [63:0] $end
$var reg 64 b expectedOut [63:0] $end
$var reg 8 c passed [7:0] $end
$var reg 257 d testType [256:0] $end
$upscope $end
$upscope $end
$scope module SingleCycleProcTest_v $end
$scope module uut $end
$scope module ALU $end
$upscope $end
$scope module DataMemory $end
$scope task initset $end
$upscope $end
$upscope $end
$scope module NextPClogic $end
$upscope $end
$scope module RegisterFile $end
$upscope $end
$scope module SignExtender $end
$upscope $end
$scope module control $end
$upscope $end
$scope module imem $end
$upscope $end
$upscope $end
$scope task allPassed $end
$upscope $end
$scope task passTest $end
$upscope $end
$upscope $end
$enddefinitions $end
#0
$dumpvars
bx d
bx c
bx b
bx a
bx `
bx _
bx ^
bx ]
bx \
bx [
bx Z
xY
bx X
bx W
bx V
bx U
bx T
bx S
bx R
bx Q
bx P
bx O
xN
xM
bx L
bx K
b0 J
b100000 I
bx H
bx G
bx F
bx E
bx D
bx C
bx B
bx A
bx @
bx ?
bx >
bx =
x<
x;
bx :
bx 9
bx 8
x7
x6
x5
bx 4
bx 3
bx 2
x1
bx 0
bx /
x.
bx -
bx ,
bx +
x*
0)
b0 (
b0 '
b0 &
b0 %
1$
0#
bx "
bx !
$end
#60000
1#
#120000
b1 '
0#
#121000
0$
#180000
1#
#240000
0Y
0N
b1 +
b1 W
b1 \
b10 >
b10 D
b10 [
0*
0;
05
16
1.
17
1<
b0 @
b0 B
b0 9
b0 L
b0 X
b0x00x ,
b0x00x T
1)
b0 =
b0 E
b0 F
b10000000000001111101001 V
b11111000010 3
b11111000010 Z
b0 0
b0 C
b0 P
b11111 -
b11111 S
b1001 2
b1001 U
b100 4
b100 O
0M
b11111000010000000000001111101001 8
b11111000010000000000001111101001 ^
b0 "
b0 ?
b0 K
b0 ]
b10 '
0#
#241000
1$
#300000
b1 A
b1 R
b1 !
b1 :
b1 H
1#
#360000
0)
b1000 =
b1000 E
b1000 F
b1000 @
b1000 B
b1000 9
b1000 L
b1000 X
b0x0x0 ,
b0x0x0 T
b10000001000001111101010 V
b1010 2
b1010 U
b1000 4
b1000 O
b11111000010000001000001111101010 8
b11111000010000001000001111101010 ^
b100 "
b100 ?
b100 K
b100 ]
b11 '
0#
#420000
b1010 A
b1010 R
b1010 !
b1010 :
b1010 H
1#
#480000
b10000 =
b10000 E
b10000 F
b10000 @
b10000 B
b10000 9
b10000 L
b10000 X
b0x0x1 ,
b0x0x1 T
b10000010000001111101011 V
b1011 2
b1011 U
b1100 4
b1100 O
b11111000010000010000001111101011 8
b11111000010000010000001111101011 ^
b1000 "
b1000 ?
b1000 K
b1000 ]
b100 '
0#
#540000
b101 A
b101 R
b101 !
b101 :
b101 H
1#
#600000
b11000 =
b11000 E
b11000 F
b11000 @
b11000 B
b11000 9
b11000 L
b11000 X
b0xx0x ,
b0xx0x T
b10000011000001111101100 V
b1100 2
b1100 U
b10000 4
b10000 O
b11111000010000011000001111101100 8
b11111000010000011000001111101100 ^
b1100 "
b1100 ?
b1100 K
b1100 ]
b101 '
0#
#660000
b111111111011111010100111110111101010110110111110111011111111 A
b111111111011111010100111110111101010110110111110111011111111 R
b111111111011111010100111110111101010110110111110111011111111 !
b111111111011111010100111110111101010110110111110111011111111 :
b111111111011111010100111110111101010110110111110111011111111 H
1#
#720000
b100000 =
b100000 E
b100000 F
b100000 @
b100000 B
b100000 9
b100000 L
b100000 X
b0xxxx ,
b0xxxx T
b10000100000001111101101 V
b1101 2
b1101 U
b10100 4
b10100 O
b11111000010000100000001111101101 8
b11111000010000100000001111101101 ^
b10000 "
b10000 ?
b10000 K
b10000 ]
b110 '
0#
#780000
b0 A
b0 R
b0 !
b0 :
b0 H
1#
#840000
b101 /
b101 G
b101 Q
b1111 A
b1111 R
bx +
bx W
bx \
b1 >
b1 D
b1 [
06
07
0<
01
b1111 =
b1111 E
b1111 F
b101 @
b101 B
b0 9
b0 L
b0 X
b1011 ,
b1011 T
b10000010110000000101001010 V
b10101010000 3
b10101010000 Z
b1010 0
b1010 C
b1010 P
b1010 -
b1010 S
b1010 2
b1010 U
b11000 4
b11000 O
b10101010000010110000000101001010 8
b10101010000010110000000101001010 ^
b10100 "
b10100 ?
b10100 K
b10100 ]
b111 '
0#
#900000
1#
#960000
b1111 A
b1111 R
b0 >
b0 D
b0 [
b1111 =
b1111 E
b1111 F
b1111 @
b1111 B
b1111 /
b1111 G
b1111 Q
b1010 ,
b1010 T
b10000010100000000110001100 V
b10001010000 3
b10001010000 Z
b1100 -
b1100 S
b1100 2
b1100 U
b11100 4
b11100 O
b10001010000010100000000110001100 8
b10001010000010100000000110001100 ^
b11000 "
b11000 ?
b11000 K
b11000 ]
b111111111011111010100111110111101010110110111110111011111111 0
b111111111011111010100111110111101010110110111110111011111111 C
b111111111011111010100111110111101010110110111110111011111111 P
b1000 '
0#
#1020000
1#
#1080000
b100 9
b100 L
b100 X
b0 A
b0 R
b11 +
b11 W
b11 \
b111 >
b111 D
b111 [
1;
0.
x7
11
b1111 =
b1111 E
b1111 F
b1111 @
b1111 B
b1111 /
b1111 G
b1111 Q
b1100 ,
b1100 T
b10001100 V
b10110100000 3
b10110100000 Z
b100 -
b100 S
b100000 4
b100000 O
b10110100000000000000000010001100 8
b10110100000000000000000010001100 ^
b11100 "
b11100 ?
b11100 K
b11100 ]
bx 0
bx C
bx P
b1001 '
0#
#1140000
1#
#1200000
b1 A
b1 R
0)
b1 =
b1 E
b1 F
bx +
bx W
bx \
b10 >
b10 D
b10 [
0;
1.
07
01
b1 @
b1 B
b0 9
b0 L
b0 X
b1 /
b1 G
b1 Q
b1001 ,
b1001 T
b11000010010000000110101101 V
b10001011000 3
b10001011000 Z
b0 0
b0 C
b0 P
b1101 -
b1101 S
b1101 2
b1101 U
b100100 4
b100100 O
b10001011000010010000000110101101 8
b10001011000010010000000110101101 ^
b100000 "
b100000 ?
b100000 K
b100000 ]
b1010 '
0#
#1260000
1#
#1320000
b110 >
b110 D
b110 [
b11000010010000000110001100 V
b11001011000 3
b11001011000 Z
b1100 -
b1100 S
b1100 2
b1100 U
b1110 A
b1110 R
b101000 4
b101000 O
b11001011000010010000000110001100 8
b11001011000010010000000110001100 ^
b1110 =
b1110 E
b1110 F
b100100 "
b100100 ?
b100100 K
b100100 ]
b1111 0
b1111 C
b1111 P
b1011 '
0#
#1380000
1#
#1440000
b1111111111111111111111111111111111111111111111111111111111111101 9
b1111111111111111111111111111111111111111111111111111111111111101 L
b1111111111111111111111111111111111111111111111111111111111111101 X
1Y
1N
xM
1)
b10 +
b10 W
b10 \
bx >
bx D
bx [
1*
x;
0.
x7
x<
x1
b1111111111111111111111111111111111111111111111111111111111111101 @
b1111111111111111111111111111111111111111111111111111111111111101 B
bx /
bx G
bx Q
b111x1 ,
b111x1 T
b11111111111111111111111101 V
b10111111 3
b10111111 Z
b11111 -
b11111 S
b11101 2
b11101 U
b0 A
b0 R
b11100 4
b11100 O
b10111111111111111111111111101 8
b10111111111111111111111111101 ^
b0 =
b0 E
b0 F
b101000 "
b101000 ?
b101000 K
b101000 ]
b0 0
b0 C
b0 P
b1100 '
0#
#1500000
1#
